Postgresql112ZhongwenWendang/README.md
Postgresql112ZhongwenWendang/__init__.py
Postgresql112ZhongwenWendang/__main__.py
Postgresql112ZhongwenWendang/file.epub
Postgresql112ZhongwenWendang/index.html
Postgresql112ZhongwenWendang/css/__init__.py
Postgresql112ZhongwenWendang/css/annotations.css
Postgresql112ZhongwenWendang/css/main.css
Postgresql112ZhongwenWendang/css/normalize.css
Postgresql112ZhongwenWendang/css/popup.css
Postgresql112ZhongwenWendang/font/__init__.py
Postgresql112ZhongwenWendang/font/fontello.eot
Postgresql112ZhongwenWendang/font/fontello.svg
Postgresql112ZhongwenWendang/font/fontello.ttf
Postgresql112ZhongwenWendang/font/fontello.woff
Postgresql112ZhongwenWendang/img/__init__.py
Postgresql112ZhongwenWendang/img/annotator-glyph-sprite.png
Postgresql112ZhongwenWendang/img/annotator-icon-sprite.png
Postgresql112ZhongwenWendang/img/apple-touch-icon.png
Postgresql112ZhongwenWendang/img/cancelfullscreen.png
Postgresql112ZhongwenWendang/img/close.png
Postgresql112ZhongwenWendang/img/fullscreen.png
Postgresql112ZhongwenWendang/img/loader.gif
Postgresql112ZhongwenWendang/img/menu-icon.png
Postgresql112ZhongwenWendang/img/save.png
Postgresql112ZhongwenWendang/img/saved.png
Postgresql112ZhongwenWendang/img/settings-s.png
Postgresql112ZhongwenWendang/img/settings.png
Postgresql112ZhongwenWendang/img/star.png
Postgresql112ZhongwenWendang/js/__init__.py
Postgresql112ZhongwenWendang/js/epub.js
Postgresql112ZhongwenWendang/js/epub.min.js
Postgresql112ZhongwenWendang/js/epub.min.map
Postgresql112ZhongwenWendang/js/hooks.min.js
Postgresql112ZhongwenWendang/js/hooks.min.map
Postgresql112ZhongwenWendang/js/reader.js
Postgresql112ZhongwenWendang/js/reader.js.map
Postgresql112ZhongwenWendang/js/reader.min.js
Postgresql112ZhongwenWendang/js/reader.min.map
Postgresql112ZhongwenWendang/js/hooks/__init__.py
Postgresql112ZhongwenWendang/js/hooks/extensions/__init__.py
Postgresql112ZhongwenWendang/js/hooks/extensions/highlight.js
postgresql_11_2_zhongwen_wendang-2024.3.5.0.dist-info/METADATA
postgresql_11_2_zhongwen_wendang-2024.3.5.0.dist-info/WHEEL
postgresql_11_2_zhongwen_wendang-2024.3.5.0.dist-info/entry_points.txt
postgresql_11_2_zhongwen_wendang-2024.3.5.0.dist-info/top_level.txt
postgresql_11_2_zhongwen_wendang-2024.3.5.0.dist-info/RECORD
